duke_agents/__init__.py
duke_agents/__version__.py
duke_agents/config.py
duke_agents/py.typed
duke_agents/agents/__init__.py
duke_agents/agents/atomic_agent.py
duke_agents/agents/base_agent.py
duke_agents/agents/codeact_agent.py
duke_agents/agents/utils.py
duke_agents/executors/__init__.py
duke_agents/executors/code_executor.py
duke_agents/executors/utils.py
duke_agents/llm/__init__.py
duke_agents/llm/mistral_client.py
duke_agents/llm/utils.py
duke_agents/models/__init__.py
duke_agents/models/atomic_models.py
duke_agents/models/codeact_models.py
duke_agents/models/memory.py
duke_agents/orchestration/__init__.py
duke_agents/orchestration/context_manager.py
duke_agents/orchestration/orchestrator.py
duke_agents/orchestration/utils.py
duke_agents-1.0.1.dist-info/licenses/AUTHORS
duke_agents-1.0.1.dist-info/licenses/LICENSE
duke_agents-1.0.1.dist-info/METADATA
duke_agents-1.0.1.dist-info/WHEEL
duke_agents-1.0.1.dist-info/top_level.txt
duke_agents-1.0.1.dist-info/RECORD
