Metadata-Version: 2.4
Name: duke-agents
Version: 1.0.1
Summary: DUKE Agents - Advanced AI Agent Framework with IPO Architecture
Author-email: Stephane MASSON <smasson@duke-ai.io>
Maintainer-email: Stephane MASSON <smasson@duke-ai.io>
License: MIT
Project-URL: Homepage, https://github.com/elmasson/duke-agents
Project-URL: Documentation, https://github.com/elmasson/duke-agents/tree/main/docs
Project-URL: Repository, https://github.com/elmasson/duke-agents.git
Project-URL: Issues, https://github.com/elmasson/duke-agents/issues
Project-URL: Changelog, https://github.com/elmasson/duke-agents/blob/main/CHANGELOG.md
Keywords: ai,agents,mistral,llm,autonomous-agents,ipo-architecture,codeact
Classifier: Development Status :: 4 - Beta
Classifier: Intended Audience :: Developers
Classifier: Topic :: Software Development :: Libraries :: Python Modules
Classifier: Topic :: Scientific/Engineering :: Artificial Intelligence
Classifier: License :: OSI Approved :: MIT License
Classifier: Programming Language :: Python :: 3
Classifier: Programming Language :: Python :: 3.8
Classifier: Programming Language :: Python :: 3.9
Classifier: Programming Language :: Python :: 3.10
Classifier: Programming Language :: Python :: 3.11
Classifier: Programming Language :: Python :: 3.12
Classifier: Operating System :: OS Independent
Classifier: Typing :: Typed
Requires-Python: >=3.8
License-File: LICENSE
License-File: AUTHORS
Requires-Dist: mistralai>=1.0.0
Requires-Dist: pydantic>=2.0.0
Requires-Dist: pyyaml>=6.0
Requires-Dist: python-dotenv>=1.0.0
Provides-Extra: dev
Requires-Dist: pytest>=7.0.0; extra == "dev"
Requires-Dist: pytest-cov>=4.0.0; extra == "dev"
Requires-Dist: pytest-asyncio>=0.21.0; extra == "dev"
Requires-Dist: black>=23.0.0; extra == "dev"
Requires-Dist: flake8>=6.0.0; extra == "dev"
Requires-Dist: mypy>=1.0.0; extra == "dev"
Requires-Dist: isort>=5.12.0; extra == "dev"
Requires-Dist: pre-commit>=3.0.0; extra == "dev"
Provides-Extra: docs
Requires-Dist: sphinx>=5.0.0; extra == "docs"
Requires-Dist: sphinx-rtd-theme>=1.2.0; extra == "docs"
Requires-Dist: sphinx-autodoc-typehints>=1.22.0; extra == "docs"
Dynamic: license-file
